debug_informer/__init__.py
debug_informer/apps.py
debug_informer/middleware.py
debug_informer/models.py
debug_informer/urls.py
debug_informer/views.py
django_debug_informer-0.4.0.dist-info/METADATA
django_debug_informer-0.4.0.dist-info/RECORD
django_debug_informer-0.4.0.dist-info/WHEEL
django_debug_informer-0.4.0.dist-info/top_level.txt
