Metadata-Version: 2.1
Name: django-debug-informer
Version: 0.4.0
Summary: A simple application that helps you to display various debug information about the Django project
Home-page: https://github.com/Gr1N/django-debug-informer
Author: Nikita Grishko
Author-email: gr1n@protonmail.com
License: UNKNOWN
Project-URL: Bug Reports, https://github.com/Gr1N/django-debug-informer/issues
Project-URL: Source, https://github.com/Gr1N/django-debug-informer
Keywords: django debug
Platform: UNKNOWN
Classifier: Development Status :: 4 - Beta
Classifier: Environment :: Web Environment
Classifier: Framework :: Django
Classifier: Intended Audience :: Developers
Classifier: License :: OSI Approved :: MIT License
Classifier: Operating System :: OS Independent
Classifier: Programming Language :: Python
Classifier: Programming Language :: Python :: 3
Classifier: Programming Language :: Python :: 3.6
Classifier: Topic :: Software Development :: Libraries :: Python Modules
Requires-Dist: django (<3.0,>=2.0)
Requires-Dist: pip (>=1.10)
